{
  "timestamp": "2025-08-21T09:11:43.943211",
  "overall_status": "critical",
  "metrics": {
    "token_discovery_rate": {
      "current_value": 1.0,
      "status": "critical",
      "last_updated": "2025-08-21T09:11:42.926711"
    },
    "approval_rate": {
      "current_value": 46.42857142857143,
      "status": "healthy",
      "last_updated": "2025-08-21T09:11:43.938174"
    },
    "api_error_rate": {
      "current_value": 0.0,
      "status": "healthy",
      "last_updated": "2025-08-21T09:11:42.926711"
    },
    "trade_execution_rate": {
      "current_value": 0,
      "status": "critical",
      "last_updated": "2025-08-21T09:11:42.926711"
    },
    "cpu_usage": {
      "current_value": 14.3,
      "status": "healthy",
      "last_updated": "2025-08-21T09:11:43.933342"
    },
    "memory_usage": {
      "current_value": 88.3,
      "status": "warning",
      "last_updated": "2025-08-21T09:11:43.938174"
    },
    "disk_usage": {
      "current_value": 95.80512018794523,
      "status": "critical",
      "last_updated": "2025-08-21T09:11:43.938174"
    },
    "api_response_time": {
      "current_value": 30,
      "status": "healthy",
      "last_updated": "2025-08-21T09:11:42.926711"
    },
    "log_activity": {
      "current_value": true,
      "status": "healthy",
      "last_updated": "2025-08-21T09:11:43.943211"
    }
  },
  "issues": [
    "CRITICAL: token_discovery_rate = 1.0 (threshold: 50)",
    "CRITICAL: trade_execution_rate = 0 (threshold: 0)",
    "WARNING: memory_usage = 88.3 (threshold: 80)",
    "CRITICAL: disk_usage = 95.80512018794523 (threshold: 95)"
  ],
  "recovery_actions": [
    "medium_recovery",
    "manual_intervention"
  ],
  "uptime": 876.857038
}